{"card_name": "Helar Ritualist", "color": "U", "rarity": "rare", "type": "Creature \u2013 Human Shaman", "number": 47, "color_identity": "WUB", "cost": "{3}{U}{U}", "rules_text": "Flying\nWhen Helar Ritualist enters or whenever you cast a spell, if {W}{B} was spent to cast it, each opponent loses 3 life and you gain 3 life. Put a +1/+1 counter on Helar Ritualist.", "pt": "3/2", "special_text": "", "shape": "normal", "set": "BYK", "loyalty": "", "notes": "https://www.artstation.com/artwork/6Rk6\n!submit2"}