{"card_name": "Edgewalker Drone", "color": "", "rarity": "common", "type": "Artifact Creature \u2013 Insect", "number": 118, "color_identity": "C", "cost": "{2}", "rules_text": "When Edgewalker Drone dies, conjure two cards named Short Sword into your hand. [i](They\u2019re Equipment artifacts that cost {1} with \u201cEquipped creature gets +1/+1\u201d and Equip {1}.)[/i]", "pt": "2/1", "special_text": "", "shape": "normal", "set": "INK", "loyalty": "", "notes": "https://www.artstation.com/artwork/w4lXg"}