{"card_name": "Upholder of Purity", "color": "W", "rarity": "mythic", "type": "Creature \u2013 Angel Soldier", "number": 18, "color_identity": "W", "cost": "{6}{W}{W}", "rules_text": "Delve [i](Each card you exile from your graveyard while casting this spell pays for {1}.)[/i]\nFlying\nIf you would lose the game, instead put Upholder of Purity on the bottom of its owner\u2019s library, and you may have your life total become 5.", "pt": "4/4", "special_text": "", "shape": "normal", "set": "BTJ", "loyalty": "", "notes": "!spectres\n!change"}