{"card_name": "Roads Once Known", "color": "G", "rarity": "common", "type": "Sorcery", "number": 86, "color_identity": "G", "cost": "{2}{G}", "rules_text": "Reveal the top three cards of your library. You may put a permanent card from among them into your hand. Put the rest into your graveyard.\nRetrace [i](You may cast this card from your graveyard by discarding a land card in addition to paying its other costs.)[/i]", "pt": "", "special_text": "", "shape": "normal", "set": "LRH", "loyalty": "", "notes": "https://www.artstation.com/artwork/e0QXkb"}