{"card_name": "Capture Brilliance", "color": "UBR", "rarity": "uncommon", "type": "Sorcery", "number": 99, "color_identity": "UBR", "cost": "{4}{U}{B}{R}", "rules_text": "Choose two or four \u2013\n\u2022 Each player draws seven cards.\n\u2022 Each opponent discards four cards.\n\u2022 Conjure three cards named Fatigue and put them on top of your library. [i](They\u2019re colorless sorceries that cost {2} with \u201cDraw a card.\u201d)[/i]\n\u2022 You may cast a card from your hand without paying its mana cost. Exile Capture Brilliance.", "pt": "", "special_text": "", "shape": "normal", "set": "ACA", "loyalty": "", "notes": "modal pact"}