{"card_name": "Imbued Creation", "color": "G", "rarity": "uncommon", "type": "Instant", "number": 100, "color_identity": "G", "cost": "{2}{G}", "rules_text": "As an additional cost to cast this spell, sacrifice a land.\n[i]Converge[/i] \u2013 Search your library for up to X basic land cards and put them onto the battlefield tapped, where X is the number of colors of mana spent to cast Imbued Creation. Then shuffle your library.", "pt": "", "special_text": "", "shape": "normal", "set": "MMC", "loyalty": "", "notes": "2k17\nCommon > Uncommon"}