{"card_name": "Resolute Captain", "color": "W", "rarity": "common", "type": "Creature \u2013 Human Soldier", "number": 15, "color_identity": "W", "cost": "{1}{W}", "rules_text": "When Resolute Captain dies, create a 1/1 red and white Soldier creature token with haste.\nReborn 2\u2013{4}{W} [i](You may cast this card from your graveyard for it\u2019s reborn cost. If you do, it enters the battlefield with two additional +1/+1 counters on it and becomes reborn. When it dies while reborn, exile it.)[/i]", "pt": "2/2", "special_text": "", "shape": "normal", "set": "MMC", "loyalty": "", "notes": ""}