{"card_name": "Indomitable Render", "color": "B", "rarity": "uncommon", "type": "Creature \u2013 Orc Warrior", "number": 56, "color_identity": "B", "cost": "{1}{B}", "rules_text": "Haste\nReborn 1\u2013{2}{B}{B} [i](You may cast this card from your graveyard for it\u2019s reborn cost. If you do, it enters the battlefield with an additional +1/+1 counter on it and becomes reborn. When it dies while reborn, exile it.)[/i]", "pt": "2/1", "special_text": "", "shape": "normal", "set": "MMC", "loyalty": "", "notes": ""}