{"card_name": "Refracted Thoughts", "color": "B", "rarity": "rare", "type": "Instant", "number": 21, "color_identity": "B", "cost": "{1}{B}", "rules_text": "Choose target player. Until end of turn, if a spell or ability that player controls would cause them to draw a card, each of their opponents draws a card instead.", "pt": "", "special_text": "", "shape": "normal", "set": "MAC", "loyalty": "", "notes": "i know we have a weirdly high amount of these effects but this has been planned for AGES and will be important for me next set\n\nfluffy: him or her\u2014>them, outside\u2014>except during (draw outside isn\u2019t in magicese but except during is, Defence Grid), that player\u2019s\u2014>theirs since there\u2019s already a that player in there, draw\u2014>draws"}